oemof/db/__init__.py
oemof/db/coastdat.py
oemof/db/config.py
oemof/db/feedin_pg.py
oemof/db/powerplants.py
oemof/db/results.py
oemof/db/tools.py
oemof/db/examples/feedinlib_example_coastdat.py
oemof.db-0.0.6.dist-info/AUTHORS.rst
oemof.db-0.0.6.dist-info/LICENSE
oemof.db-0.0.6.dist-info/METADATA
oemof.db-0.0.6.dist-info/WHEEL
oemof.db-0.0.6.dist-info/top_level.txt
oemof.db-0.0.6.dist-info/RECORD
