Metadata-Version: 2.1
Name: oemof.db
Version: 0.0.6
Summary: Open Energy Modelling Framework - An extension for all database related things
Home-page: https://github.com/oemof/oemof.db
Author: oemof developer group
Author-email: oemof@rl-institut.de
License: MIT
Project-URL: Documentation, https://oemofdb.readthedocs.io/
Project-URL: Changelog, https://oemofdb.readthedocs.io/en/latest/changelog.html
Project-URL: Issue Tracker, https://github.com/oemof/oemof.db/issues
Platform: UNKNOWN
Classifier: Development Status :: 4 - Beta
Classifier: Intended Audience :: Developers
Classifier: License :: OSI Approved :: MIT License
Classifier: Operating System :: Unix
Classifier: Operating System :: POSIX
Classifier: Operating System :: Microsoft :: Windows
Classifier: Programming Language :: Python
Classifier: Programming Language :: Python :: 3
Classifier: Programming Language :: Python :: 3.5
Classifier: Programming Language :: Python :: 3.6
Classifier: Programming Language :: Python :: 3.7
Classifier: Programming Language :: Python :: 3.8
Classifier: Programming Language :: Python :: Implementation :: CPython
Classifier: Topic :: Utilities
Requires-Python: !=3.0.*, !=3.1.*, !=3.2.*, !=3.3.*, !=3.4.*
Requires-Dist: oemof
Requires-Dist: sqlalchemy (>=1.0)
Requires-Dist: keyring (>=4.0)
Requires-Dist: shapely
Requires-Dist: psycopg2
Requires-Dist: keyrings.alt
Requires-Dist: pandas (>=0.19.1)
